cipherShad0w/__init__.py
cipherShad0w/cli.py
cipherShad0w/core.py
cipherShad0w-0.1.7.2.dist-info/LICENSE
cipherShad0w-0.1.7.2.dist-info/METADATA
cipherShad0w-0.1.7.2.dist-info/WHEEL
cipherShad0w-0.1.7.2.dist-info/entry_points.txt
cipherShad0w-0.1.7.2.dist-info/top_level.txt
cipherShad0w-0.1.7.2.dist-info/RECORD
