Metadata-Version: 2.2
Name: cipherShad0w
Version: 0.1.7.2
Summary: Utilities by Jannis
Home-page: https://github.com/cipher-shad0w/sorting_visualizer
Author: cipher-shad0w
Author-email: Jannis.krija@icloud.com
Classifier: Programming Language :: Python :: 3
Classifier: License :: OSI Approved :: MIT License
Classifier: Operating System :: OS Independent
Requires-Python: >=3.6
License-File: LICENSE
Dynamic: author
Dynamic: author-email
Dynamic: classifier
Dynamic: description
Dynamic: description-content-type
Dynamic: home-page
Dynamic: requires-python
Dynamic: summary
